DataConsumer/DataType.py
DataConsumer/RangeType.py
DataConsumer/__init__.py
DataConsumer/test.py
DataConsumer/__pycache__/DataType.cpython-310.pyc
DataConsumer-0.0.16.dist-info/LICENSE
DataConsumer-0.0.16.dist-info/METADATA
DataConsumer-0.0.16.dist-info/WHEEL
DataConsumer-0.0.16.dist-info/top_level.txt
DataConsumer-0.0.16.dist-info/RECORD
