Metadata-Version: 2.1
Name: DataConsumer
Version: 0.0.16
Summary: 实现对数据的快速处理以及对带有不确定度的数据的运算和修约
Home-page: https://github.com/lsyxiaopang/auto-Dataconsuming
Author: Lisongyu
Author-email: lisongyuandy@foxmail.com
License: MIT
Platform: UNKNOWN
Classifier: License :: OSI Approved :: MIT License
Classifier: Programming Language :: Python
Classifier: Programming Language :: Python :: 3
Classifier: Programming Language :: Python :: 3.6
Classifier: Programming Language :: Python :: Implementation :: CPython
Classifier: Programming Language :: Python :: Implementation :: PyPy
Requires-Python: >=3.0.0
License-File: LICENSE
Requires-Dist: typing
Provides-Extra: packages_needed_for_datatype
Requires-Dist: pandas ; extra == 'packages_needed_for_datatype'
Requires-Dist: numpy ; extra == 'packages_needed_for_datatype'
Requires-Dist: scipy ; extra == 'packages_needed_for_datatype'
